MANIFEST.in
README.md
demo.py
setup.py
SZlabeler/__init__.py
SZlabeler/catalog.py
SZlabeler/exceptions.py
SZlabeler/jsongen.ipynb
SZlabeler/label_classifier.py
SZlabeler/tokenizer.py
SZlabeler.egg-info/PKG-INFO
SZlabeler.egg-info/SOURCES.txt
SZlabeler.egg-info/dependency_links.txt
SZlabeler.egg-info/top_level.txt
SZlabeler/.ipynb_checkpoints/jsongen-checkpoint.ipynb
SZlabeler/__pycache__/__init__.cpython-37.pyc
SZlabeler/__pycache__/__init__.cpython-38.pyc
SZlabeler/__pycache__/label_classifier.cpython-37.pyc
SZlabeler/__pycache__/label_classifier.cpython-38.pyc
SZlabeler/config/hybrid_rule_label.json
SZlabeler/config/labels.txt
SZlabeler/config/rule_label.json
data/labels.txt
dist/SZlabeler-0.0.3.tar.gz
dist/SZlabeler-0.0.4.tar.gz
picture/Rule-Structure.png